unicycle_controller/__init__.py
unicycle_controller/controller.py
unicycle_controller/cost_map.py
unicycle_controller/dynamics.py
unicycle_controller/training.py
unicycle_controller/visualization.py
unicycle_controller-0.1.0.dist-info/LICENSE
unicycle_controller-0.1.0.dist-info/METADATA
unicycle_controller-0.1.0.dist-info/WHEEL
unicycle_controller-0.1.0.dist-info/top_level.txt
unicycle_controller-0.1.0.dist-info/RECORD
