Metadata-Version: 2.1
Name: unicycle-controller
Version: 0.1.0
Summary: A package for unicycle control and reachability analysis
Home-page: https://github.com/catplotlib/verified_control
Author: Puja Chaudhury
Author-email: catplotlib@gmail.com
Classifier: Programming Language :: Python :: 3
Classifier: License :: OSI Approved :: MIT License
Classifier: Operating System :: OS Independent
Requires-Python: >=3.7
License-File: LICENSE
Requires-Dist: jax
Requires-Dist: jaxlib
Requires-Dist: jax-verify
Requires-Dist: optax
Requires-Dist: matplotlib
Requires-Dist: numpy
